tensorboard_plugin_customizable_plots/__init__.py
tensorboard_plugin_customizable_plots/plugin.py
tensorboard_plugin_customizable_plots/static/dashboard.js
tensorboard_plugin_customizable_plots/static/index.html
tensorboard_plugin_customizable_plots/static/index.js
tensorboard_plugin_customizable_plots/static/package-lock.json
tensorboard_plugin_customizable_plots/static/package.json
tensorboard_plugin_customizable_plots/static/css/githubIcon.svg
tensorboard_plugin_customizable_plots/static/css/mui-icons.css
tensorboard_plugin_customizable_plots/static/css/roboto.css
tensorboard_plugin_customizable_plots/static/css/styles.css
tensorboard_plugin_customizable_plots/static/css/iconfont/MaterialIcons-Regular.ttf
tensorboard_plugin_customizable_plots/static/css/iconfont/MaterialIconsOutlined-Regular.otf
tensorboard_plugin_customizable_plots/static/css/iconfont/MaterialIconsRound-Regular.otf
tensorboard_plugin_customizable_plots/static/css/iconfont/MaterialIconsSharp-Regular.otf
tensorboard_plugin_customizable_plots/static/css/iconfont/MaterialIconsTwoTone-Regular.otf
tensorboard_plugin_customizable_plots/static/css/iconfont/README.md
tensorboard_plugin_customizable_plots/static/dest/dashboard.js
tensorboard_plugin_customizable_plots/static/libs/MathJax.js
tensorboard_plugin_customizable_plots/static/libs/create-plotly-component.js
tensorboard_plugin_customizable_plots/static/libs/material-ui.development.js
tensorboard_plugin_customizable_plots/static/libs/plotly-latest.min-1.58.5.js
tensorboard_plugin_customizable_plots/static/libs/plotly-latest.min.js
tensorboard_plugin_customizable_plots/static/libs/react-dom.development.js
tensorboard_plugin_customizable_plots/static/libs/react.development.js
tensorboard_plugin_customizable_plots/static/libs/config/general_config.js
tensorboard_plugin_customizable_plots/static/libs/config/layout_attributes.js
tensorboard_plugin_customizable_plots/static/libs/config/plot_config.js
tensorboard_plugin_customizable_plots-1.1.3.dist-info/LICENSE
tensorboard_plugin_customizable_plots-1.1.3.dist-info/METADATA
tensorboard_plugin_customizable_plots-1.1.3.dist-info/WHEEL
tensorboard_plugin_customizable_plots-1.1.3.dist-info/entry_points.txt
tensorboard_plugin_customizable_plots-1.1.3.dist-info/top_level.txt
tensorboard_plugin_customizable_plots-1.1.3.dist-info/RECORD
