Metadata-Version: 2.1
Name: tensorboard_plugin_customizable_plots
Version: 1.1.3
Summary: A plugin for TensorBoard to customize and export Scalar plots
License-File: LICENSE
